{
  "id": "political-communication-bdde349c6d2c",
  "doi": "10.1080/10584609.2026.2617224",
  "url": "https://doi.org/10.1080/10584609.2026.2617224",
  "journalName": "POLITICAL COMMUNICATION",
  "journalSlug": "political-communication",
  "issn": "1058-4609",
  "publishedAt": "2026-01-15T12:59:40.000Z",
  "authors": [
    "Michael Brüggemann",
    "Christel W.",
    "van Eck",
    "Shota Gelovani",
    "Hendrik Meyer",
    "Ashley Muddiman",
    "Louisa Pröschel",
    "Hartmut Wessler",
    "Hamburg",
    "Germanyb Amsterdam",
    "Amsterdam",
    "The Netherlandsc",
    "Mannheim",
    "Germanyd",
    "The",
    "Lawrence",
    "USAMichael Brüggemann",
    "is a",
    "professor of Communication",
    "Climate, and Science Communication at the"
  ],
  "source": "rss",
  "fetchedAt": "2026-04-16T07:07:29.030Z",
  "language": "en",
  "raw_title": "What Kind of Depolarization Should We Aim For? Making Communication Transformative",
  "raw_abstract": "",
  "raw_keywords": [],
  "title_en": "What Kind of Depolarization Should We Aim For? Making Communication Transformative",
  "title_zh": "我们应该追求何种去极化？让沟通变得具有变革性",
  "abstract_en": "",
  "abstract_zh": "",
  "keywords_en": [],
  "keywords_zh": [],
  "inferred_keywords_en": [
    "depolarization",
    "political communication",
    "transformative communication",
    "public discourse",
    "media effects"
  ],
  "inferred_keywords_zh": [
    "去极化",
    "政治传播",
    "变革性沟通",
    "公共话语",
    "媒体效果"
  ],
  "plain_summary_zh": "这篇文章探讨了在政治沟通中应该追求什么样的去极化目标，以及如何让沟通变得具有变革性，能够真正改变人们的观点和对话方式。",
  "plain_summary_en": "This article examines what kind of depolarization goals we should pursue in political communication and how to make communication transformative, capable of genuinely changing people's perspectives and dialogue patterns.",
  "research_direction_zh": "研究政治沟通中的去极化策略和变革性沟通模式，探索如何通过沟通实践减少社会分裂并促进建设性对话。",
  "research_direction_en": "Investigating depolarization strategies and transformative communication models in political communication, exploring how communication practices can reduce social division and promote constructive dialogue.",
  "method_tags_zh": [
    "理论分析",
    "文献综述"
  ],
  "method_tags_en": [
    "theoretical analysis",
    "literature review"
  ]
}
